{
  "repuestos": [
    {
      "Articulo": "EECRL018",
      "Descripcion": "DRIVE PARA MOTOR BRUSHLESS SPD8NS/K005 8A 380/480V SYSTEM (6800002275/5949501464)",
      "Cantidad": 1,
      "UM": "UN"
    },
    {
      "Articulo": "EEENC015",
      "Descripcion": "ENCODER INCREMENTAL D = 63 DE BRIDA CUADRADA CENTRADO 31.75mm EJE MACIZO = 9.52mm 1000 PPR 5 VDC LINE DRIVER CON CONECTOR AXIAL ELTRA (EH63D1000S5L9X6MA.272/C7653100001)",
      "Cantidad": 1,
      "UM": "UN"
    },
    {
      "Articulo": "EEVAF016",
      "Descripcion": "DRIVE PARA MOTOR BRUSHLESS MODELO SPD16N/K0005 16A 380/440V SYSTEM (6800002276)",
      "Cantidad": 1,
      "UM": "UN"
    },
    {
      "Articulo": "EEVAF017",
      "Descripcion": "DRIVE BRUSHLES SPD16N/K0005 16A 380-480VAC  SBCMODELO TWIN5 5+5A V38 SYSTEM (5949501354/EX.6800000742)",
      "Cantidad": 1,
      "UM": "UN"
    },
    {
      "Articulo": "EMACT046",
      "Descripcion": "CILINDRO NEUMATICO DOBLE EFECTO D = 50mm C = 125mm (9660116603)",
      "Cantidad": 1,
      "UM": "UN"
    },
    {
      "Articulo": "EMACT098",
      "Descripcion": "CILINDRO TOPE C92SDB D=32mm C=40mm PARA RODILLERA FIFO FACON SYSTEM (C9660103369)",
      "Cantidad": 1,
      "UM": "UN"
    },
    {
      "Articulo": "EMACT101",
      "Descripcion": "CILINDRO APERTURA CIERRE PINZA D = 63mm C = 100mm  P = 1mpa PARA FALCON SYSTEM (9660106345)",
      "Cantidad": 2,
      "UM": "UN"
    },
    {
      "Articulo": "EMBAN043",
      "Descripcion": "BANDA DENTADA RPP14 ANCHO = 40mm L = 3150mm SYSTEM (9343331502/C9343331502)",
      "Cantidad": 1,
      "UM": "UN"
    },
    {
      "Articulo": "EMBAS026",
      "Descripcion": "BASE GANASCE PINZAS DINT = 117 X 100 X 50mm FALCON MILLENNIUM SYSTEM (8326282401)",
      "Cantidad": 4,
      "UM": "UN"
    },
    {
      "Articulo": "EMBIS008",
      "Descripcion": "BRIDA POSTERIOR HEMBRA ALUMINIO D = 10mm PARA CILINDRO NEUMATICO D = 32mm SYSTEM (9666100085/C9666100085)",
      "Cantidad": 1,
      "UM": "UN"
    },
    {
      "Articulo": "EMBIS009",
      "Descripcion": "BISAGRA BRIDA MACHO CON EJE D = 12mm L = 68mm PARA CILINDRO D = 50mm SYSTEM (9666100042/C9666100042)",
      "Cantidad": 1,
      "UM": "UN"
    },
    {
      "Articulo": "EMBUJ131",
      "Descripcion": "BUJE PARA RUEDA DENTADA GLY. PBG DINT = 12mm DEXT = 14mm E = 9mm SYSTEM (9244012010/C9244012010)",
      "Cantidad": 4,
      "UM": "UN"
    },
    {
      "Articulo": "EMBUJ157",
      "Descripcion": "BUJE D = 35-20mm DINT = 15mm L = 23mm PARA TRACCION EJE X SYSTEM (8124315000)",
      "Cantidad": 1,
      "UM": "UN"
    },
    {
      "Articulo": "EMCAT087",
      "Descripcion": "CATALINA LOCA RODILLERA FIFO CON RODAMIENTO Z = 16 P = 1/2in DINT = 16mm PARA FALCON SYSTEM(C9131010003)",
      "Cantidad": 4,
      "UM": "UN"
    },
    {
      "Articulo": "EMCAT088",
      "Descripcion": "CATALINA PLASTICA DE NYLON FIJO Z  = 11 P = 1/2in DINT = 14mm (9282050020)",
      "Cantidad": 10,
      "UM": "UN"
    },
    {
      "Articulo": "EMCAT089",
      "Descripcion": "CATALINA PLASTICA DE NYLON LOCO Z = 11 P = 1/2in DINT = 15mm SYSTEM (9282050013/C9282050013)",
      "Cantidad": 10,
      "UM": "UN"
    },
    {
      "Articulo": "EMCRE012",
      "Descripcion": "CREMALLERA M = 1 A = 15mm CON EJE D = 10mm ROSCA M10 X 0.75 L = 180mm PARA PINZAS FALCON SYSTEM (8113215301/C8113215301)",
      "Cantidad": 4,
      "UM": "UN"
    },
    {
      "Articulo": "EMEJE196",
      "Descripcion": "EJE PARA RUEDA DE GOMA DE D1 = 55mm D2 = 90mm D3 = 50mm L = 135mm FALCON SYSTEM (C8111711000)",
      "Cantidad": 1,
      "UM": "UN"
    },
    {
      "Articulo": "EMEJE199",
      "Descripcion": "EJE D1 = 30mm D2 = 40mm D3 = 90mm D4 = 50mm L = 317mm SYSTEM (C8111534402)",
      "Cantidad": 1,
      "UM": "UN"
    },
    {
      "Articulo": "EMELV050",
      "Descripcion": "ELECTROVALVULA MONOESTABLE 5/2 G 1/8 24VDC SMC SY5120-5YO-01F-Q FALCON SYSTEM (9640100045/C9640100045)",
      "Cantidad": 4,
      "UM": "UN"
    },
    {
      "Articulo": "EMELV051",
      "Descripcion": "ELECTROVALVULA FALCON SYSTEM SY5220-5YO-01F-Q (9640100048)",
      "Cantidad": 2,
      "UM": "UN"
    },
    {
      "Articulo": "EMENG049",
      "Descripcion": "ENGRANAJE RECTO DEXT = 29mm DINT = 14mm M = 1 Z = 27 L = 17mm DF14 PALETIZADOR SYSTEM (8113016600/C8113016600)",
      "Cantidad": 2,
      "UM": "UN"
    },
    {
      "Articulo": "EMENG061",
      "Descripcion": "ENGRANAJE CONICO Z = 16 CON M4 SYSTEM (8113013730)",
      "Cantidad": 2,
      "UM": "UN"
    },
    {
      "Articulo": "EMGUI110",
      "Descripcion": "GUIA NADELLA PARA CILINDRO JAULA FS32TT L = 663mm 4 AGUJEROS D = 6.5mm (8125042230)",
      "Cantidad": 1,
      "UM": "UN"
    },
    {
      "Articulo": "EMGUI139",
      "Descripcion": "GUIA APERTURA CIERRE PINZAL = 524mm A = 42mm E = 7mm PARA FALCON SYSTEM (8125050830)",
      "Cantidad": 2,
      "UM": "UN"
    },
    {
      "Articulo": "EMGUI170",
      "Descripcion": "GUIA POLIZENE DE 15 X 12mm L = 2000mm (C9903200000) SYSTEM",
      "Cantidad": 4,
      "UM": "M"
    },
    {
      "Articulo": "EMMNV004",
      "Descripcion": "MANIVELA HEMBRA DE 237.7 X 62 X 12mm VOLTEADOR DE CAJAS SYSTEM (8320813000)",
      "Cantidad": 2,
      "UM": "UN"
    },
    {
      "Articulo": "EMMOT118",
      "Descripcion": "MOTOR BRUSHLESS 14230155243MB644 3.93KW 15Nm BRAKE DE 24VDC 0.8ADC D = 24mm SYSTEM (9110930025)",
      "Cantidad": 1,
      "UM": "UN"
    },
    {
      "Articulo": "EMMTR039",
      "Descripcion": "MOTOREDUCTOR CON ELECTROFRENO HBZ71B4 0.37KW 1380 220V I = 70 MRIV50 D  = 27mm (9111302002)",
      "Cantidad": 1,
      "UM": "UN"
    },
    {
      "Articulo": "EMMTR079",
      "Descripcion": "MOTOREDUCTOR NMRV040 0.45KW 1680RPM 220V I = 30 (9111304405/C9111304405)",
      "Cantidad": 1,
      "UM": "UN"
    },
    {
      "Articulo": "EMMTR080",
      "Descripcion": "MOTOREDUCTOR NMRV040 0.45KW 1700RPM 220V I=20 SYSTEM (C9111307011)",
      "Cantidad": 1,
      "UM": "UN"
    },
    {
      "Articulo": "EMPAS023",
      "Descripcion": "PASADOR RUEDA D1 = 15mm D2 = 20mm L = 74mm CON ROSCA INTERIOR M10 X 20mm FALCON SYSTEM (8111534000)",
      "Cantidad": 6,
      "UM": "UN"
    },
    {
      "Articulo": "EMPAS025",
      "Descripcion": "PASADOR D1 = 15mm D2 = 12mm L = 76mm CON ROSCA INTERIOR M10 X 21mm RUEDA FALCON SYSTEM (8111534300)",
      "Cantidad": 2,
      "UM": "UN"
    },
    {
      "Articulo": "EMPER064",
      "Descripcion": "PERNO LIBRE CONCENTRICO M10 X 15mm NADELLA FRN32 SYSTEM (9213503210/C9213503210)",
      "Cantidad": 8,
      "UM": "UN"
    },
    {
      "Articulo": "EMPER065",
      "Descripcion": "PERNO LIBRE EXCENTRICO M10 X 15mm NADELLA FRNR32 SYSTEM (9213503211/C9213503211)",
      "Cantidad": 8,
      "UM": "UN"
    },
    {
      "Articulo": "EMPER067",
      "Descripcion": "PERNO LOCO EXCENTRICO M6 X 12mm FRR22 SYSTEM (9213502202/C9213502202)",
      "Cantidad": 2,
      "UM": "UN"
    },
    {
      "Articulo": "EMPER069",
      "Descripcion": "PERNO RUEDA DENTADA M8 X 18mm L = 42mm PARA PINZA PINZA FALCON SYSTEM (8111527502)",
      "Cantidad": 2,
      "UM": "UN"
    },
    {
      "Articulo": "EMPNZ001",
      "Descripcion": "PINZA PARA VOLTEADOR DE 273 X 50 X 4mm CAJA FALCON (C8320814500)",
      "Cantidad": 2,
      "UM": "UN"
    },
    {
      "Articulo": "EMPOL054",
      "Descripcion": "POLEA DENTADA T10 Z = 20 D = 61.8mm L = 20mm DINT = 15mm PARA EJE X FALCON SYSTEM (8112035800)",
      "Cantidad": 1,
      "UM": "UN"
    },
    {
      "Articulo": "EMPOL059",
      "Descripcion": "POLEA DE SINCRONIZACION Z = 28 RPP14M-40 DINT = 31mm L = 54mm DEXT = 128mm SYSTEM (8112033702)",
      "Cantidad": 2,
      "UM": "UN"
    },
    {
      "Articulo": "EMRCT105",
      "Descripcion": "REDUCTOR ORTOGONAL MRCI63 I = 12.6 D1 = 24mm D2 = 147mm D3 = 30mm (9112111100)",
      "Cantidad": 1,
      "UM": "UN"
    },
    {
      "Articulo": "EMRUE028",
      "Descripcion": "RUEDA FIJA DEXT = 200mm DINT = 55mm L = 80mm EJE X SYSTEM (8128027000)",
      "Cantidad": 2,
      "UM": "UN"
    },
    {
      "Articulo": "EMRUE030",
      "Descripcion": "RUEDA DE GOMA DEXT = 81mm L = 28mm DINT = 12mm SYSTEM (8128102930)",
      "Cantidad": 2,
      "UM": "UN"
    },
    {
      "Articulo": "EMRUE031",
      "Descripcion": "RUEDA DE GOMA EMPACADORA FALCON SYSTEM DEXT = 100mm DINT = 20mm L = 40mm SYSTEM (9281100004/C9281100004)",
      "Cantidad": 4,
      "UM": "UN"
    },
    {
      "Articulo": "EMRUE032",
      "Descripcion": "RUEDA DE GOMA  DEXT = 125mm DINT = 15mm L = 30mm EMPACADORA FALCON SYSTEM (9281125005)",
      "Cantidad": 4,
      "UM": "UN"
    },
    {
      "Articulo": "EMRUE057",
      "Descripcion": "RUEDA D = 80mm DDF = 42-35 LR SYSTEM (8128026800)",
      "Cantidad": 6,
      "UM": "UN"
    },
    {
      "Articulo": "EMRUE090",
      "Descripcion": "RUEDA LOCA PARA EJE X DE 200X50 SYSTEM (9281200003/C9281200003)",
      "Cantidad": 2,
      "UM": "UN"
    },
    {
      "Articulo": "EMSEP006",
      "Descripcion": "DISTANCIADOR DE GOMA DEXT = 20mm DINT = 7.5mm  L = 40mm SYSTEM (8154100701)",
      "Cantidad": 1,
      "UM": "UN"
    },
    {
      "Articulo": "EMSOP039",
      "Descripcion": "SOPORTE PARA MOTOR VOLTEADOR DE CAJAS 370 X 36 X 125.5mm D = 10mm SYSTEM (C8320911300)",
      "Cantidad": 1,
      "UM": "UN"
    },
    {
      "Articulo": "EMSOP083",
      "Descripcion": "SOPORTE PARA CILINDRO PINZA L = 145 X 105 X 102mm FALCON SYSTEM (8320510905/C8320510905)",
      "Cantidad": 2,
      "UM": "UN"
    },
    {
      "Articulo": "EMSOP108",
      "Descripcion": "SOPORTE PLATO DE ALUMINIO DE 524 X 30 X 15mm SYSTEM (8321518400/C8321518400)",
      "Cantidad": 2,
      "UM": "UN"
    },
    {
      "Articulo": "EMSOP130",
      "Descripcion": "SOPORTE EN L PARA CILINDRO RIVALTIN L = 70 X 105 X 40mm E = 4mm  2AS6.5 IFD12 (8320885501)",
      "Cantidad": 2,
      "UM": "UN"
    },
    {
      "Articulo": "EMSOP166",
      "Descripcion": "SOPORTE 75X50mm EASY LINE SYSTEM (9542000030/C9542000030)",
      "Cantidad": 1,
      "UM": "UN"
    },
    {
      "Articulo": "EMSOP198",
      "Descripcion": "SOPORTE PARA CILINDRO 146 X 103 X 311mm (8320814401/8320814403/C8320814403)",
      "Cantidad": 2,
      "UM": "UN"
    },
    {
      "Articulo": "UMBAN004",
      "Descripcion": "BANDA DE POLIURETANO T10 LR = 16  EJE X FALCON SYSTEM (9994050000/80880100)",
      "Cantidad": 25,
      "UM": "M"
    },
    {
      "Articulo": "UMCAD001",
      "Descripcion": "CADENA TRANSMISION 08-B1",
      "Cantidad": 4,
      "UM": "UN"
    },
    {
      "Articulo": "UMCAT065",
      "Descripcion": "RODILLO TENSOR D = 50mm RODILLERA FIFO PARA FALCON MILLENNIUM SYSTEM (C8128103030)",
      "Cantidad": 4,
      "UM": "UN"
    },
    {
      "Articulo": "UMPOL192",
      "Descripcion": "POLEA LOCA D1 = 69mm D2 = 60mm DINT = 28-25-28mm LR = 21 PARA BANDA T10 EJE X (8112211701)",
      "Cantidad": 2,
      "UM": "UN"
    },
    {
      "Articulo": "UMRDL030",
      "Descripcion": "RODILLO L = 400mm D = 32mm PARA CINTA MOVIL SYSTEM(C9282032045)",
      "Cantidad": 10,
      "UM": "UN"
    },
    {
      "Articulo": "UMROD137",
      "Descripcion": "RODAMIENTO RIGIDO DE BOLAS SKF 6302 2ZC3",
      "Cantidad": 12,
      "UM": "UN"
    },
    {
      "Articulo": "UMROD424",
      "Descripcion": "RODAMIENTO RIGIDO DE BOLAS SKF 6002-2RSH/C3",
      "Cantidad": 2,
      "UM": "UN"
    },
    {
      "Articulo": "UMROD427",
      "Descripcion": "RODAMIENTO RIGIDO DE BOLAS SKF 6010-2RS1 C3",
      "Cantidad": 4,
      "UM": "UN"
    },
    {
      "Articulo": "UMROD468",
      "Descripcion": "RODAMIENTO RIGIDO DE BOLAS SKF 6001-2RSH C3",
      "Cantidad": 4,
      "UM": "UN"
    },
    {
      "Articulo": "UMTUE014",
      "Descripcion": "TUERCA AUTOBLOCANTE GUK00 D = 10 X 0.75mm SYSTEM (9324010000/C9324010000)",
      "Cantidad": 4,
      "UM": "UN"
    }
  ]
}